PygameEnhanced/__init__.py
PygameEnhanced/app.py
PygameEnhanced/templates/index.html
pygameenhanced-1.4.4.dist-info/LICENSE
pygameenhanced-1.4.4.dist-info/METADATA
pygameenhanced-1.4.4.dist-info/WHEEL
pygameenhanced-1.4.4.dist-info/top_level.txt
pygameenhanced-1.4.4.dist-info/RECORD
