Metadata-Version: 2.2
Name: PygameEnhanced
Version: 1.4.4
Summary: An enhanced set of utilities for Pygame.
Author-email: unknown <unknown@email.com>
License: MIT
Project-URL: Homepage, https://github.com/Github3742/PygameEnhanced
Project-URL: Documentation, https://yourdocsurl.com
Project-URL: Repository, https://github.com/Github3742/PygameEnhanced
Requires-Python: >=3.7
License-File: LICENSE
Requires-Dist: Flask
